notebook_setup/__init__.py
notebook_setup-1.2.dist-info/METADATA
notebook_setup-1.2.dist-info/WHEEL
notebook_setup-1.2.dist-info/licenses/LICENSE
notebook_setup-1.2.dist-info/RECORD
